df/__init__.py
df/checkpoint.py
df/config.py
df/deepfilternet.py
df/deepfilternet2.py
df/deepfilternet3.py
df/deepfilternetmf.py
df/enhance.py
df/evaluation_utils.py
df/io.py
df/logger.py
df/loss.py
df/lr.py
df/model.py
df/modules.py
df/multiframe.py
df/scripts/dnsmos.py
df/scripts/dnsmos_dns5.py
df/scripts/dnsmos_v2.py
df/scripts/export.py
df/scripts/filter_dnsmos.py
df/scripts/fix_n_samples_hdf5.py
df/scripts/list_attrs_in_hdf5.py
df/scripts/model_summary.py
df/scripts/plot_lrs.py
df/scripts/plot_spec.py
df/scripts/plot_summaries.py
df/scripts/prepare_data.py
df/scripts/print_model.py
df/scripts/sample_from_hdf5.py
df/scripts/split_hdf5.py
df/scripts/test_df.py
df/scripts/test_dns_2020.py
df/scripts/test_noisy_dnsmos.py
df/scripts/test_voicebank_demand.py
df/scripts/trim_silence_hdf5.py
df/sepm.py
df/stoi.py
df/train.py
df/utils.py
df/version.py
df/visualization.py
deepfilternet_fix-0.0.3.dist-info/LICENSE
deepfilternet_fix-0.0.3.dist-info/LICENSE-APACHE
deepfilternet_fix-0.0.3.dist-info/LICENSE-MIT
deepfilternet_fix-0.0.3.dist-info/METADATA
deepfilternet_fix-0.0.3.dist-info/WHEEL
deepfilternet_fix-0.0.3.dist-info/entry_points.txt
deepfilternet_fix-0.0.3.dist-info/RECORD
