Metadata-Version: 2.3
Name: deepfilternet_fix
Version: 0.0.3
Summary: Noise supression using deep filtering (fixed version)
License: MIT
Keywords: noise reduction,neural network
Author: Hendrik Schröter
Requires-Python: >=3.11,<4.0
Classifier: License :: OSI Approved :: MIT License
Classifier: Programming Language :: Python
Classifier: Programming Language :: Python :: 3
Classifier: Programming Language :: Python :: 3.11
Classifier: Programming Language :: Python :: 3.12
Classifier: Programming Language :: Python :: 3.13
Classifier: Programming Language :: Rust
Classifier: Topic :: Multimedia :: Sound/Audio :: Speech
Classifier: Topic :: Software Development :: Libraries :: Application Frameworks
Classifier: Topic :: Software Development :: Libraries :: Python Modules
Classifier: Topic :: Utilities
Provides-Extra: dnsmos-local
Provides-Extra: eval
Provides-Extra: soundfile
Provides-Extra: train
Requires-Dist: appdirs (>=1.4,<2.0)
Requires-Dist: deepfilterlib (>=0.5.6)
Requires-Dist: icecream (>=2,<3) ; extra == "train"
Requires-Dist: loguru (>=0.5)
Requires-Dist: numpy (>=2.0,<2.5)
Requires-Dist: onnxruntime (>=1.15,<2.0) ; extra == "dnsmos-local"
Requires-Dist: packaging (>=23,<25)
Requires-Dist: pesq (>=0.0.3,<0.0.5) ; extra == "eval"
Requires-Dist: pystoi (>=0.3,<0.5) ; extra == "eval"
Requires-Dist: requests (>=2.27,<3.0)
Requires-Dist: scipy (>=1,<2) ; extra == "eval"
Requires-Dist: soundfile (>=0.10,<0.13) ; extra == "soundfile"
Requires-Dist: sympy (>=1.6)
Project-URL: Repository, https://github.com/Rikorose/DeepFilterNet
